mlyzed/__init__.py
mlyzed/_verison.py
mlyzed/arrhenius.py
mlyzed/hop_events.py
mlyzed/metrics.py
mlyzed/msd.py
mlyzed/pdf.py
mlyzed/pipeline.py
mlyzed/trajectory.py
mlyzed/utils.py
mlyzed-0.2.1.dist-info/LICENSE
mlyzed-0.2.1.dist-info/METADATA
mlyzed-0.2.1.dist-info/WHEEL
mlyzed-0.2.1.dist-info/top_level.txt
mlyzed-0.2.1.dist-info/zip-safe
mlyzed-0.2.1.dist-info/RECORD
