Metadata-Version: 2.1
Name: mlyzed
Version: 0.2.1
Summary: Molecular dynamics post-processing toolbox
Home-page: https://github.com/dembart/mlyzed
Author: Artem Dembitskiy
Author-email: art.dembitskiy@gmail.com
License: MIT
Keywords: MD,trajectory,diffusion,conductivity,unwrapping
Platform: UNKNOWN
Classifier: Programming Language :: Python :: 3.8
Classifier: Programming Language :: Python :: 3.9
Classifier: Programming Language :: Python :: 3.10
Classifier: Programming Language :: Python :: 3.11
Classifier: Programming Language :: Python :: 3.12
Classifier: License :: OSI Approved :: MIT License
Classifier: Operating System :: OS Independent
License-File: LICENSE
Requires-Dist: numpy
Requires-Dist: scipy
Requires-Dist: ase
Requires-Dist: vesin
Requires-Dist: tqdm
Requires-Dist: networkx
